package android.support.v7.widget;

import android.content.Context;
import android.graphics.Canvas;
import android.support.v7.a.a;
import android.util.AttributeSet;
import android.widget.SeekBar;

public class w extends SeekBar {
  private final x a = new x(this);
  
  public w(Context paramContext, AttributeSet paramAttributeSet) { this(paramContext, paramAttributeSet, a.a.seekBarStyle); }
  
  public w(Context paramContext, AttributeSet paramAttributeSet, int paramInt) {
    super(paramContext, paramAttributeSet, paramInt);
    this.a.a(paramAttributeSet, paramInt);
  }
  
  protected void drawableStateChanged() {
    super.drawableStateChanged();
    this.a.c();
  }
  
  public void jumpDrawablesToCurrentState() {
    super.jumpDrawablesToCurrentState();
    this.a.b();
  }
  
  protected void onDraw(Canvas paramCanvas) { // Byte code:
    //   0: aload_0
    //   1: monitorenter
    //   2: aload_0
    //   3: aload_1
    //   4: invokespecial onDraw : (Landroid/graphics/Canvas;)V
    //   7: aload_0
    //   8: getfield a : Landroid/support/v7/widget/x;
    //   11: aload_1
    //   12: invokevirtual a : (Landroid/graphics/Canvas;)V
    //   15: aload_0
    //   16: monitorexit
    //   17: return
    //   18: astore_2
    //   19: aload_0
    //   20: monitorexit
    //   21: aload_2
    //   22: athrow
    // Exception table:
    //   from	to	target	type
    //   2	15	18	finally }
}


/* Location:              C:\Users\Siyam\Desktop\Home automation with java source files\Decompile tools\New folder\dex2jar-0.0.9.15-master\classes_dex2jar.jar!\android\support\v7\widget\w.class
 * Java compiler version: 6 (50.0)
 * JD-Core Version:       1.0.7
 */